requests_magpie.py
requests_magpie-0.3.0.dist-info/LICENSE
requests_magpie-0.3.0.dist-info/WHEEL
requests_magpie-0.3.0.dist-info/METADATA
requests_magpie-0.3.0.dist-info/RECORD
